mcp_guardian/__init__.py
mcp_guardian/guardian.py
mcp_guardian/runner.py
mcp_guardian-0.1.1.dist-info/METADATA
mcp_guardian-0.1.1.dist-info/WHEEL
mcp_guardian-0.1.1.dist-info/top_level.txt
mcp_guardian-0.1.1.dist-info/RECORD
